clustviz/__init__.py
clustviz/agglomerative.py
clustviz/birch.py
clustviz/clara.py
clustviz/clarans.py
clustviz/cure.py
clustviz/dbscan.py
clustviz/denclue.py
clustviz/optics.py
clustviz/pam.py
clustviz/utils.py
clustviz/chameleon/__init__.py
clustviz/chameleon/chameleon.py
clustviz/chameleon/chameleon2.py
clustviz/chameleon/graphtools.py
clustviz-0.0.6b0.dist-info/LICENSE
clustviz-0.0.6b0.dist-info/METADATA
clustviz-0.0.6b0.dist-info/WHEEL
clustviz-0.0.6b0.dist-info/top_level.txt
clustviz-0.0.6b0.dist-info/RECORD
