Metadata-Version: 2.1
Name: clustviz
Version: 0.0.6b0
Summary: A 2D clustering algorithms visualization package
Home-page: https://github.com/guglielmosanchini/ClustViz
Author: Guglielmo Sanchini
Author-email: guglielmosanchini@gmail.com
License: UNKNOWN
Platform: UNKNOWN
Classifier: Programming Language :: Python :: 3
Classifier: License :: OSI Approved :: MIT License
Classifier: Operating System :: OS Independent
Requires-Python: >=3.6
Requires-Dist: metis-python
Requires-Dist: pandas (>=1.0.1)
Requires-Dist: numpy (>=1.18.1)
Requires-Dist: networkx (<=2.5)
Requires-Dist: pyclustering (>=0.9.3.1)
Requires-Dist: imageio (>=2.6.1)
Requires-Dist: tqdm (>=4.42.1)
Requires-Dist: matplotlib (<=3.3.3)
Requires-Dist: scipy (>=1.4.1)
Requires-Dist: graphviz (==0.13.2)
Requires-Dist: scikit-learn (>=0.22.1)
